transfer_flatfile_format/__init__.py
transfer_flatfile_format/__main__.py
transfer_flatfile_format/cli.py
transfer_flatfile_format/packages/__init__.py
transfer_flatfile_format/packages/google_sheet.py
transfer_flatfile_format-0.1.3.dist-info/LICENSE
transfer_flatfile_format-0.1.3.dist-info/WHEEL
transfer_flatfile_format-0.1.3.dist-info/METADATA
transfer_flatfile_format-0.1.3.dist-info/RECORD
