Metadata-Version: 2.1
Name: transfer-flatfile-format
Version: 0.1.3
Summary: Move data inbetween different Amazon flatfile formats to the correct locations.
License: GPL-3.0-or-later
Keywords: flatfile,amazon,gsheet
Author: Sebastian Fricke
Author-email: sebastian.fricke.linux@gmail.com
Requires-Python: >=3.7,<4.0
Classifier: License :: OSI Approved :: GNU General Public License v3 or later (GPLv3+)
Classifier: Programming Language :: Python :: 3
Classifier: Programming Language :: Python :: 3.7
Classifier: Programming Language :: Python :: 3.8
Requires-Dist: google-api-python-client (>=1.11.0,<2.0.0)
Requires-Dist: google-auth-httplib2 (>=0.0.4,<0.0.5)
Requires-Dist: numpy (>=1.19.1,<2.0.0)
Requires-Dist: pandas (>=1.1.1,<2.0.0)
